odoo/addons/shopinvader_demo_app/README.rst
odoo/addons/shopinvader_demo_app/__init__.py
odoo/addons/shopinvader_demo_app/__manifest__.py
odoo/addons/shopinvader_demo_app/hooks.py
odoo/addons/shopinvader_demo_app/data/ir_export_product.xml
odoo/addons/shopinvader_demo_app/demo/product_brand_demo.xml
odoo/addons/shopinvader_demo_app/demo/product_product_demo.xml
odoo/addons/shopinvader_demo_app/demo/se_backend_elasticsearch_demo.xml
odoo/addons/shopinvader_demo_app/demo/storage_backend_demo.xml
odoo/addons/shopinvader_demo_app/readme/CONTRIBUTORS.rst
odoo/addons/shopinvader_demo_app/readme/DESCRIPTION.rst
odoo/addons/shopinvader_demo_app/static/description/index.html
odoo12_addon_shopinvader_demo_app-12.0.2.0.5.dist-info/METADATA
odoo12_addon_shopinvader_demo_app-12.0.2.0.5.dist-info/WHEEL
odoo12_addon_shopinvader_demo_app-12.0.2.0.5.dist-info/top_level.txt
odoo12_addon_shopinvader_demo_app-12.0.2.0.5.dist-info/RECORD
