Metadata-Version: 2.1
Name: odoo12-addon-shopinvader-demo-app
Version: 12.0.2.0.5
Summary: Shopinvader Demo App
Home-page: https://acsone.eu/
Author: ACSONE SA/NV
License: AGPL-3
Platform: UNKNOWN
Classifier: Programming Language :: Python
Classifier: Framework :: Odoo
Classifier: License :: OSI Approved :: GNU Affero General Public License v3
Requires-Python: >=3.5
Requires-Dist: odoo12-addon-product-brand
Requires-Dist: odoo12-addon-shopinvader
Requires-Dist: odoo12-addon-shopinvader-assortment
Requires-Dist: odoo12-addon-shopinvader-delivery-carrier
Requires-Dist: odoo12-addon-shopinvader-elasticsearch
Requires-Dist: odoo12-addon-shopinvader-guest-mode
Requires-Dist: odoo12-addon-shopinvader-image
Requires-Dist: odoo12-addon-shopinvader-locomotive
Requires-Dist: odoo12-addon-shopinvader-locomotive-elasticsearch
Requires-Dist: odoo12-addon-shopinvader-locomotive-guest-mode
Requires-Dist: odoo12-addon-shopinvader-payment-manual
Requires-Dist: odoo12-addon-shopinvader-payment-stripe
Requires-Dist: odoo12-addon-shopinvader-product-stock
Requires-Dist: odoo (<12.1dev,>=12.0a)
